README.md
htmlparsing.py
setup.py
htmlparsing.egg-info/PKG-INFO
htmlparsing.egg-info/SOURCES.txt
htmlparsing.egg-info/dependency_links.txt
htmlparsing.egg-info/not-zip-safe
htmlparsing.egg-info/requires.txt
htmlparsing.egg-info/top_level.txt