Metadata-Version: 1.1
Name: htmlparsing
Version: 0.1.5
Summary: Pure HTML parsing library.
Home-page: https://github.com/gaojiuli/htmlparsing
Author: Jiuli Gao
Author-email: gaojiuli@gmail.com
License: UNKNOWN
Platform: UNKNOWN
Classifier: Development Status :: 5 - Production/Stable
Classifier: Intended Audience :: Developers
Classifier: Programming Language :: Python :: 3.5
Classifier: Programming Language :: Python :: 3.6
